imap_client/__init__.py
imap_client/imap_client.py
imap_client-0.1.8.dist-info/LICENSE
imap_client-0.1.8.dist-info/METADATA
imap_client-0.1.8.dist-info/WHEEL
imap_client-0.1.8.dist-info/top_level.txt
imap_client-0.1.8.dist-info/RECORD
