Metadata-Version: 2.1
Name: imap-client
Version: 0.1.8
Summary: Simple client providing an object interface for imaplib
Home-page: https://github.com/dawidl022/imap-client
Author: dawidl022
License: MIT
Platform: UNKNOWN
